countriespop/__init__.py
countriespop/cli.py
countriespop/data/countries_table.csv
countriespop-0.1.1.dist-info/METADATA
countriespop-0.1.1.dist-info/WHEEL
countriespop-0.1.1.dist-info/entry_points.txt
countriespop-0.1.1.dist-info/RECORD
